{
  "cardId": 85106525,
  "name": "Bonfire",
  "sourceFile": "official/c85106525.lua",
  "parserVersion": "v7-gate-strip",
  "parsedAt": "2026-04-24",
  "listedNames": [],
  "listedSeries": [],
  "summonProcedures": [],
  "effects": [
    {
      "id": "e1",
      "categories": [
        "CATEGORY_TOHAND",
        "CATEGORY_SEARCH"
      ],
      "types": [
        "EFFECT_TYPE_ACTIVATE"
      ],
      "properties": [],
      "events": [
        "EVENT_FREE_CHAIN"
      ],
      "descriptionStringId": "0",
      "countLimit": {
        "count": 1,
        "key": "id"
      },
      "target": {
        "name": "s.target",
        "opaque": false,
        "simpleFilter": {
          "predicates": [
            {
              "kind": "levelBelow",
              "value": 4
            },
            {
              "kind": "race",
              "value": "RACE_PYRO"
            },
            {
              "kind": "ableToHand"
            }
          ],
          "complete": true
        }
      },
      "operation": {
        "name": "s.activate",
        "opaque": false,
        "simpleFilter": {
          "predicates": [
            {
              "kind": "levelBelow",
              "value": 4
            },
            {
              "kind": "race",
              "value": "RACE_PYRO"
            },
            {
              "kind": "ableToHand"
            }
          ],
          "complete": true
        },
        "actions": [
          {
            "kind": "send-to-hand",
            "method": "SendtoHand",
            "target": "g",
            "argHints": [
              "nil",
              "REASON_EFFECT"
            ]
          },
          {
            "kind": "confirm",
            "method": "ConfirmCards",
            "target": "1-tp",
            "argHints": [
              "g"
            ]
          }
        ]
      }
    }
  ],
  "coverage": {
    "totalEffects": 1,
    "totalFunctionRefs": 2,
    "fullyDecoded": 2,
    "partiallyDecoded": 0,
    "opaqueUndecoded": 0
  },
  "warnings": []
}